eventropy/__init__.py
eventropy/tools.py
eventropy-1.0.2.dist-info/top_level.txt
eventropy-1.0.2.dist-info/METADATA
eventropy-1.0.2.dist-info/DESCRIPTION.rst
eventropy-1.0.2.dist-info/metadata.json
eventropy-1.0.2.dist-info/WHEEL
eventropy-1.0.2.dist-info/RECORD
