Metadata-Version: 2.0
Name: eventropy
Version: 1.0.2
Summary: Events Management
Home-page: https://github.com/phenicle/eventropy
Author: Phenicle
Author-email: pheniclebeefheart@gmail.com
License: Mozilla Public License 2.0 (MPL 2.0)
Platform: UNKNOWN
Requires-Dist: cfgpy
Requires-Dist: psycopg2
